.gitignore
CHANGES.rst
MANIFEST.in
README.rst
README.txt
bootstrap.py
buildout.cfg
buildout317.cfg
setup.py
collective/__init__.py
collective/__init__.pyc
collective.emaillogin.egg-info/PKG-INFO
collective.emaillogin.egg-info/SOURCES.txt
collective.emaillogin.egg-info/dependency_links.txt
collective.emaillogin.egg-info/entry_points.txt
collective.emaillogin.egg-info/namespace_packages.txt
collective.emaillogin.egg-info/not-zip-safe
collective.emaillogin.egg-info/requires.txt
collective.emaillogin.egg-info/top_level.txt
collective/emaillogin/TODO.txt
collective/emaillogin/__init__.py
collective/emaillogin/configure.zcml
collective/emaillogin/enable.cfg
collective/emaillogin/migration.py
collective/emaillogin/profiles.zcml
collective/emaillogin/rebuild_i18n.sh
collective/emaillogin/skins.zcml
collective/emaillogin/utils.py
collective/emaillogin/locales/collective.emaillogin.pot
collective/emaillogin/locales/de/LC_MESSAGES/collective.emaillogin.mo
collective/emaillogin/locales/de/LC_MESSAGES/collective.emaillogin.po
collective/emaillogin/locales/nl/LC_MESSAGES/collective.emaillogin.mo
collective/emaillogin/locales/nl/LC_MESSAGES/collective.emaillogin.po
collective/emaillogin/profiles/default/metadata.xml
collective/emaillogin/profiles/default/skins.xml
collective/emaillogin/skins/emaillogin/join_form.cpt
collective/emaillogin/skins/emaillogin/join_form.cpt.metadata
collective/emaillogin/skins/emaillogin/join_form_validate.vpy
collective/emaillogin/skins/emaillogin/logged_in.cpy
collective/emaillogin/skins/emaillogin/logged_in.cpy.metadata
collective/emaillogin/skins/emaillogin/login_form.cpt
collective/emaillogin/skins/emaillogin/login_form.cpt.metadata
collective/emaillogin/skins/emaillogin/login_form_validate.vpy
collective/emaillogin/skins/emaillogin/login_form_validate.vpy.metadata
collective/emaillogin/skins/emaillogin/mail_password_form.pt
collective/emaillogin/skins/emaillogin/mail_password_form.pt.metadata
collective/emaillogin/skins/emaillogin/personalize.cpy
collective/emaillogin/skins/emaillogin/personalize.cpy.metadata
collective/emaillogin/skins/emaillogin/pwreset_form.cpt
collective/emaillogin/skins/emaillogin/pwreset_form.cpt.metadata
collective/emaillogin/skins/emaillogin/pwreset_invalid.pt
collective/emaillogin/skins/emaillogin/pwreset_invalid.pt.metadata
