Metadata-Version: 1.0
Name: collective.emaillogin
Version: 1.3
Summary: Allow logins with email address rather than login name.
Home-page: https://github.com/collective/collective.emaillogin
Author: Guido Wesdorp
Author-email: guido@pragmagik.com
License: GPL
Platform: UNKNOWN
Classifier: Framework :: Plone
Classifier: Framework :: Plone :: 3.2
Classifier: Framework :: Plone :: 3.3
Classifier: Framework :: Zope2
Classifier: Framework :: Zope3
Classifier: Programming Language :: Python
Classifier: Topic :: Software Development :: Libraries :: Python Modules
